payok_aio/__init__.py
payok_aio/api.py
payok_aio/const.py
payok_aio/exceptions.py
payok_aio/models.py
payok_aio/utils.py
payok_aio-0.1.7.dist-info/LICENSE
payok_aio-0.1.7.dist-info/METADATA
payok_aio-0.1.7.dist-info/WHEEL
payok_aio-0.1.7.dist-info/RECORD
