Metadata-Version: 2.1
Name: payok-aio
Version: 0.1.7
Summary: 
Author: BazZziliuS
Author-email: bazzzil123@gmail.com
Requires-Python: >=3.9
Classifier: Programming Language :: Python :: 3
Classifier: Programming Language :: Python :: 3.9
Classifier: Programming Language :: Python :: 3.10
Classifier: Programming Language :: Python :: 3.11
Classifier: Programming Language :: Python :: 3.12
Requires-Dist: aiohttp (>=3.9.3,<4.0.0)
Requires-Dist: certifi (>=2024.2.2,<2025.0.0)
Requires-Dist: pydantic (>=2.6.3,<3.0.0)
